camouflage_decryptor/__about__.py
camouflage_decryptor/__init__.py
camouflage_decryptor/__main__.py
camouflage_decryptor/decryptor.py
camouflage_decryptor/key.py
camouflage_decryptor/keytool.py
camouflage_decryptor/cli/__init__.py
camouflage_decryptor-0.3.4.dist-info/METADATA
camouflage_decryptor-0.3.4.dist-info/WHEEL
camouflage_decryptor-0.3.4.dist-info/entry_points.txt
camouflage_decryptor-0.3.4.dist-info/licenses/LICENSE.txt
camouflage_decryptor-0.3.4.dist-info/RECORD
