Metadata-Version: 2.1
Name: camouflage-decryptor
Version: 0.3.4
Project-URL: Documentation, https://github.com/anjomro/camouflage-decryptor#readme
Project-URL: Issues, https://github.com/anjomro/camouflage-decryptor/issues
Project-URL: Source, https://github.com/anjomro/camouflage-decryptor
Author-email: anjomro <py@anjomro.de>
License-Expression: EUPL-1.2
License-File: LICENSE.txt
Classifier: Development Status :: 4 - Beta
Classifier: Programming Language :: Python
Classifier: Programming Language :: Python :: 3.7
Classifier: Programming Language :: Python :: 3.8
Classifier: Programming Language :: Python :: 3.9
Classifier: Programming Language :: Python :: 3.10
Classifier: Programming Language :: Python :: 3.11
Classifier: Programming Language :: Python :: Implementation :: CPython
Classifier: Programming Language :: Python :: Implementation :: PyPy
Requires-Python: >=3.7
Requires-Dist: click
Requires-Dist: requests
